{
  "command": "show",
  "query": "logs",
  "status_filter": "open",
  "total": 0,
  "findings": [],
  "config": {
    "review_max_age_days": 30,
    "holistic_max_age_days": 30,
    "generate_scorecard": true,
    "badge_path": "scorecard.png",
    "exclude": [],
    "ignore": [],
    "ignore_metadata": {},
    "zone_overrides": {},
    "review_dimensions": [],
    "review_allow_custom_dimensions": false,
    "review_custom_dimensions": [],
    "large_files_threshold": 0,
    "props_threshold": 0,
    "finding_noise_budget": 10,
    "finding_noise_global_budget": 0,
    "target_strict_score": 95,
    "languages": {}
  }
}
